{
  "date": "2026-04-11",
  "code": "xshg",
  "region": "south",
  "province": "Hậu Giang",
  "shortName": "XSHG",
  "scheme": "southCentral",
  "specialPrize": "104888",
  "prizes": [
    {
      "label": "Giải tám",
      "numbers": [
        "85"
      ]
    },
    {
      "label": "Giải bảy",
      "numbers": [
        "932"
      ]
    },
    {
      "label": "Giải sáu",
      "numbers": [
        "5605",
        "6638",
        "8414"
      ]
    },
    {
      "label": "Giải năm",
      "numbers": [
        "0354"
      ]
    },
    {
      "label": "Giải tư",
      "numbers": [
        "99626",
        "36758",
        "94469",
        "63000",
        "17206",
        "46346",
        "94822"
      ]
    },
    {
      "label": "Giải ba",
      "numbers": [
        "23217",
        "30055"
      ]
    },
    {
      "label": "Giải nhì",
      "numbers": [
        "98847"
      ]
    },
    {
      "label": "Giải nhất",
      "numbers": [
        "95985"
      ]
    },
    {
      "label": "Đặc biệt",
      "numbers": [
        "104888"
      ]
    }
  ],
  "sourceName": "XSKT HTML",
  "sourceUrl": "https://xskt.com.vn/xshg/30-ngay",
  "updatedAt": "2026-06-19T13:41:19.028Z",
  "fetchedAt": "2026-06-19T13:41:19.028Z",
  "dataSource": "html"
}