{
  "date": "2026-01-17",
  "code": "xsla",
  "region": "south",
  "province": "Long An",
  "shortName": "XSLA",
  "scheme": "southCentral",
  "specialPrize": "384224",
  "prizes": [
    {
      "label": "Giải tám",
      "numbers": [
        "74"
      ]
    },
    {
      "label": "Giải bảy",
      "numbers": [
        "385"
      ]
    },
    {
      "label": "Giải sáu",
      "numbers": [
        "5597",
        "6123",
        "4680"
      ]
    },
    {
      "label": "Giải năm",
      "numbers": [
        "0812"
      ]
    },
    {
      "label": "Giải tư",
      "numbers": [
        "50898",
        "17924",
        "74476",
        "46614",
        "23060",
        "16961",
        "26082"
      ]
    },
    {
      "label": "Giải ba",
      "numbers": [
        "02861",
        "31120"
      ]
    },
    {
      "label": "Giải nhì",
      "numbers": [
        "72469"
      ]
    },
    {
      "label": "Giải nhất",
      "numbers": [
        "23770"
      ]
    },
    {
      "label": "Đặc biệt",
      "numbers": [
        "384224"
      ]
    }
  ],
  "sourceName": "XSKT HTML",
  "sourceUrl": "https://xskt.com.vn/xsla/30-ngay",
  "updatedAt": "2026-06-19T13:41:31.461Z",
  "fetchedAt": "2026-06-19T13:41:31.461Z",
  "dataSource": "html"
}