{
  "date": "2026-01-24",
  "code": "xsla",
  "region": "south",
  "province": "Long An",
  "shortName": "XSLA",
  "scheme": "southCentral",
  "specialPrize": "145400",
  "prizes": [
    {
      "label": "Giải tám",
      "numbers": [
        "34"
      ]
    },
    {
      "label": "Giải bảy",
      "numbers": [
        "427"
      ]
    },
    {
      "label": "Giải sáu",
      "numbers": [
        "0225",
        "0269",
        "2506"
      ]
    },
    {
      "label": "Giải năm",
      "numbers": [
        "1447"
      ]
    },
    {
      "label": "Giải tư",
      "numbers": [
        "59352",
        "53192",
        "24300",
        "18105",
        "21869",
        "99781",
        "04275"
      ]
    },
    {
      "label": "Giải ba",
      "numbers": [
        "37435",
        "68369"
      ]
    },
    {
      "label": "Giải nhì",
      "numbers": [
        "82824"
      ]
    },
    {
      "label": "Giải nhất",
      "numbers": [
        "91392"
      ]
    },
    {
      "label": "Đặc biệt",
      "numbers": [
        "145400"
      ]
    }
  ],
  "sourceName": "XSKT HTML",
  "sourceUrl": "https://xskt.com.vn/xsla/30-ngay",
  "updatedAt": "2026-06-19T13:41:31.461Z",
  "fetchedAt": "2026-06-19T13:41:31.461Z",
  "dataSource": "html"
}