{
  "date": "2026-04-12",
  "code": "xstth",
  "region": "central",
  "province": "Thừa Thiên Huế",
  "shortName": "XSTTH",
  "scheme": "southCentral",
  "specialPrize": "878653",
  "prizes": [
    {
      "label": "Giải tám",
      "numbers": [
        "03"
      ]
    },
    {
      "label": "Giải bảy",
      "numbers": [
        "175"
      ]
    },
    {
      "label": "Giải sáu",
      "numbers": [
        "7861",
        "4841",
        "0910"
      ]
    },
    {
      "label": "Giải năm",
      "numbers": [
        "9862"
      ]
    },
    {
      "label": "Giải tư",
      "numbers": [
        "17701",
        "82340",
        "46935",
        "23528",
        "96803",
        "47018",
        "65014"
      ]
    },
    {
      "label": "Giải ba",
      "numbers": [
        "87746",
        "73391"
      ]
    },
    {
      "label": "Giải nhì",
      "numbers": [
        "63011"
      ]
    },
    {
      "label": "Giải nhất",
      "numbers": [
        "29371"
      ]
    },
    {
      "label": "Đặc biệt",
      "numbers": [
        "878653"
      ]
    }
  ],
  "sourceName": "XSKT HTML",
  "sourceUrl": "https://xskt.com.vn/xstth/30-ngay",
  "updatedAt": "2026-06-19T13:59:27.822Z",
  "fetchedAt": "2026-06-19T13:59:27.822Z",
  "dataSource": "html"
}