{
  "date": "2026-05-24",
  "code": "xsmn",
  "region": "south",
  "province": "miền Nam",
  "shortName": "XSMN",
  "scheme": "southCentral",
  "specialPrize": "347955",
  "prizes": [
    {
      "label": "Giải tám",
      "numbers": [
        "24"
      ]
    },
    {
      "label": "Giải bảy",
      "numbers": [
        "451"
      ]
    },
    {
      "label": "Giải sáu",
      "numbers": [
        "8106",
        "0925",
        "7041"
      ]
    },
    {
      "label": "Giải năm",
      "numbers": [
        "0784"
      ]
    },
    {
      "label": "Giải tư",
      "numbers": [
        "70785",
        "28511",
        "79826",
        "99360",
        "71671",
        "14799",
        "09801"
      ]
    },
    {
      "label": "Giải ba",
      "numbers": [
        "99364",
        "36047"
      ]
    },
    {
      "label": "Giải nhì",
      "numbers": [
        "53112"
      ]
    },
    {
      "label": "Giải nhất",
      "numbers": [
        "14907"
      ]
    },
    {
      "label": "Đặc biệt",
      "numbers": [
        "347955"
      ]
    }
  ],
  "sourceName": "XSKT HTML",
  "sourceUrl": "https://xskt.com.vn/xsmn/30-ngay",
  "updatedAt": "2026-06-19T15:08:18.119Z",
  "fetchedAt": "2026-06-19T15:08:18.119Z",
  "dataSource": "html"
}