{
  "date": "2026-06-05",
  "code": "xsmn",
  "region": "south",
  "province": "miền Nam",
  "shortName": "XSMN",
  "scheme": "southCentral",
  "specialPrize": "591978",
  "prizes": [
    {
      "label": "Giải tám",
      "numbers": [
        "05"
      ]
    },
    {
      "label": "Giải bảy",
      "numbers": [
        "047"
      ]
    },
    {
      "label": "Giải sáu",
      "numbers": [
        "4348",
        "2195",
        "9893"
      ]
    },
    {
      "label": "Giải năm",
      "numbers": [
        "7761"
      ]
    },
    {
      "label": "Giải tư",
      "numbers": [
        "26194",
        "55029",
        "99548",
        "05196",
        "16311",
        "58269",
        "96560"
      ]
    },
    {
      "label": "Giải ba",
      "numbers": [
        "10957",
        "79050"
      ]
    },
    {
      "label": "Giải nhì",
      "numbers": [
        "03923"
      ]
    },
    {
      "label": "Giải nhất",
      "numbers": [
        "17894"
      ]
    },
    {
      "label": "Đặc biệt",
      "numbers": [
        "591978"
      ]
    }
  ],
  "sourceName": "XSKT HTML",
  "sourceUrl": "https://xskt.com.vn/xsmn/30-ngay",
  "updatedAt": "2026-06-20T11:54:42.668Z",
  "fetchedAt": "2026-06-20T11:54:42.668Z",
  "dataSource": "html"
}